Metadata-Version: 2.1
Name: dsstd67-distributions
Version: 0.1
Summary: Gaussian and Binomial distributions
Author: Kathryn Jones
Author-email: someone@someemail.com
